LICENSE.txt
setup.py
libnexus/__init__.py
libnexus.egg-info/PKG-INFO
libnexus.egg-info/SOURCES.txt
libnexus.egg-info/dependency_links.txt
libnexus.egg-info/top_level.txt
libnexus/Console/Command.py
libnexus/Console/Writeout.py
libnexus/Console/__init__.py
libnexus/Filehandling/Directory.py
libnexus/Filehandling/File.py
libnexus/Filehandling/Format.py
libnexus/Filehandling/Indexing.py
libnexus/Filehandling/__init__.py
libnexus/Security/Enigma.py
libnexus/Security/__init__.py
libnexus/Time/Await.py
libnexus/Time/Stopwatch.py
libnexus/Time/__init__.py
libnexus/Wrappers/DynamicVariable.py
libnexus/Wrappers/Except.py
libnexus/Wrappers/__init__.py