Metadata-Version: 2.1
Name: libnexus
Version: 0a0
Summary: Create a simple yet effective server with and connect to it with a simple client!
Home-page: https://github.com/shauncameron
Author: Shaun Cameron
Author-email: shauncameron1303@gmail.com
License: MIT
Platform: UNKNOWN
